judini/__init__.py
judini/codegpt.py
judini/types.py
judini/utils.py
judini-0.1.12.dist-info/LICENSE
judini-0.1.12.dist-info/METADATA
judini-0.1.12.dist-info/WHEEL
judini-0.1.12.dist-info/top_level.txt
judini-0.1.12.dist-info/RECORD
