Metadata-Version: 2.1
Name: judini
Version: 0.1.12
Summary: CodeGPT python package
Home-page: https://github.com/JudiniLabs/judini-python
Author: Judini Inc.
Author-email: daniel@judini.ai
Classifier: Programming Language :: Python :: 3
Classifier: License :: OSI Approved :: GNU General Public License v3 (GPLv3)
Classifier: Operating System :: OS Independent
Requires-Python: >=3.7
License-File: LICENSE
Requires-Dist: requests >=2.31.0
Requires-Dist: python-dotenv >=1.0.0
Requires-Dist: pydantic >=2.5.2
